astho_updater/__init__.py
astho_updater/astho_updater.py
astho_updater/exceptions.py
astho_updater/logger.py
AsthoUpdater-0.2.6.dist-info/LICENSE
AsthoUpdater-0.2.6.dist-info/METADATA
AsthoUpdater-0.2.6.dist-info/WHEEL
AsthoUpdater-0.2.6.dist-info/top_level.txt
AsthoUpdater-0.2.6.dist-info/RECORD
