Metadata-Version: 2.1
Name: AsthoUpdater
Version: 0.2.6
Summary: A lib for update files written in Python.
Home-page: https://github.com/Asthowen/AsthoUpdater
Author: Asthowen
Author-email: contact@asthowen.fr
License: GNU v3.0
Platform: UNKNOWN
Requires-Python: >= 3.6
License-File: LICENSE
Requires-Dist: aiohttp
Requires-Dist: aiofiles
Requires-Dist: async-timeout
